{
  "indexes": [
    {
      "collectionGroup": "gear_reservations",
      "queryScope": "COLLECTION",
      "fields": [
        { "fieldPath": "status", "order": "ASCENDING" },
        { "fieldPath": "userUid", "order": "ASCENDING" },
        { "fieldPath": "blockStartIso", "order": "ASCENDING" }
      ]
    },
    {
      "collectionGroup": "gear_reservations",
      "queryScope": "COLLECTION",
      "fields": [
        { "fieldPath": "status", "order": "ASCENDING" },
        { "fieldPath": "blockStartIso", "order": "ASCENDING" }
      ]
    },
    {
      "collectionGroup": "gear_favorites",
      "queryScope": "COLLECTION",
      "fields": [
        { "fieldPath": "uid", "order": "ASCENDING" },
        { "fieldPath": "category", "order": "ASCENDING" }
      ]
    }
  ],
  "fieldOverrides": []
}